hellow_world/__init__.py
hellow_world/greet.py
hellow_world-0.1.2.dist-info/METADATA
hellow_world-0.1.2.dist-info/WHEEL
hellow_world-0.1.2.dist-info/RECORD
