Metadata-Version: 2.1
Name: hellow_world
Version: 0.1.2
Summary: 
Home-page: https://github.com/dakohhh/hellow-world
License: MIT
Author: dakohhh
Author-email: wiizzydreadmill@gmail.com
Requires-Python: >=3.9,<4.0
Classifier: License :: OSI Approved :: MIT License
Classifier: Programming Language :: Python :: 3
Classifier: Programming Language :: Python :: 3.9
Classifier: Programming Language :: Python :: 3.10
Classifier: Programming Language :: Python :: 3.11
Classifier: Programming Language :: Python :: 3.12
Project-URL: Repository, https://github.com/dakohhh/hellow-world
